pathnavigator/__init__.py
pathnavigator/att_name_convertor.py
pathnavigator/folder.py
pathnavigator/pathnavigator.py
pathnavigator/shortcut.py
pathnavigator/utils.py
pathnavigator-0.6.3.dist-info/METADATA
pathnavigator-0.6.3.dist-info/WHEEL
pathnavigator-0.6.3.dist-info/licenses/LICENSE
pathnavigator-0.6.3.dist-info/RECORD
