Metadata-Version: 2.3
Name: pathnavigator
Version: 0.6.3
Summary: A Python library for efficient directory and file navigation
Author-email: Chung-Yi Lin <philip928lin@gmail.com>
License: MIT
License-File: LICENSE
Keywords: PathNavigator,directory,environment,file,manager,path,pathnavigator,project
Requires-Dist: pyyaml
Provides-Extra: dev
Requires-Dist: ipython; extra == 'dev'
Provides-Extra: lint
Requires-Dist: pre-commit>=2.20.0; extra == 'lint'
